{"E(RIMP2 (OS))": {"E(RIMP2 (OS))": -0.4699203230264094}, "E(RIMP2 (SS))": {"E(RIMP2 (SS))": -0.09869416425386213}, "E(RIMP2)": {"E(RIMP2)": -0.5686144872802715}, "E(RIMP2) SOS": {"E(RIMP2) SOS": -0.6108964199343322}, "Final E(HF)": {"Final E(HF)": -1451.6189261251322}, "filename": "json_logs/SI5H12_1_95.json", "finish_time": {"time": "Sat Jul 29 20:38:45 2023\n", "total_time": 22.710036281}, "start_time": {"time": "Sat Jul 29 20:38:22 2023\n"}, "title": "/scratch/kx58/jm0124/tempJsons/SI5H12_1_95.json", "total_energy": {"total_energy": -1452.1875406124125}}