{"E(RIMP2 (OS))": {"E(RIMP2 (OS))": -1.6324696830519412}, "E(RIMP2 (SS))": {"E(RIMP2 (SS))": -0.6040686707034092}, "E(RIMP2)": {"E(RIMP2)": -2.2365383537553503}, "E(RIMP2) SOS": {"E(RIMP2) SOS": -2.1222105879675235}, "Final E(HF)": {"Final E(HF)": -682.2361946733381}, "filename": "json_logs/tryptophan_12.json", "finish_time": {"time": "Sun Jul 30 11:15:30 2023\n", "total_time": 18.592351381}, "start_time": {"time": "Sun Jul 30 11:15:12 2023\n"}, "title": "/scratch/kx58/jm0124/tempJsons/tryptophan_12.json", "total_energy": {"total_energy": -684.4727330270935}}