{"E(RIMP2 (OS))": {"E(RIMP2 (OS))": -2.225442885324113}, "E(RIMP2 (SS))": {"E(RIMP2 (SS))": -0.7874792627819908}, "E(RIMP2)": {"E(RIMP2)": -3.0129221481061035}, "E(RIMP2) SOS": {"E(RIMP2) SOS": -2.893075750921347}, "Final E(HF)": {"Final E(HF)": -945.5719360610992}, "filename": "json_logs/GLY_b_18.json", "finish_time": {"time": "Sat Jul 29 20:42:28 2023\n", "total_time": 26.759949555}, "start_time": {"time": "Sat Jul 29 20:42:01 2023\n"}, "title": "/scratch/kx58/jm0124/tempJsons/GLY_b_18.json", "total_energy": {"total_energy": -948.5848582092053}}