{"E(RIMP2 (OS))": {"E(RIMP2 (OS))": -2.2241386923550355}, "E(RIMP2 (SS))": {"E(RIMP2 (SS))": -0.7873438827932214}, "E(RIMP2)": {"E(RIMP2)": -3.011482575148257}, "E(RIMP2) SOS": {"E(RIMP2) SOS": -2.891380300061546}, "Final E(HF)": {"Final E(HF)": -945.5709087989469}, "filename": "json_logs/GLY_b_49.json", "finish_time": {"time": "Sat Jul 29 20:40:35 2023\n", "total_time": 26.194874954}, "start_time": {"time": "Sat Jul 29 20:40:09 2023\n"}, "title": "/scratch/kx58/jm0124/tempJsons/GLY_b_49.json", "total_energy": {"total_energy": -948.5823913740952}}