{"E(RIMP2 (OS))": {"E(RIMP2 (OS))": -1.8566364886515803}, "E(RIMP2 (SS))": {"E(RIMP2 (SS))": -0.6700590630225542}, "E(RIMP2)": {"E(RIMP2)": -2.5266955516741345}, "E(RIMP2) SOS": {"E(RIMP2) SOS": -2.4136274352470544}, "Final E(HF)": {"Final E(HF)": -760.2962589177534}, "filename": "json_logs/1_21.json", "finish_time": {"time": "Wed Aug  2 09:06:58 2023\n", "total_time": 20.95781075}, "start_time": {"time": "Wed Aug  2 09:06:38 2023\n"}, "title": "/scratch/kx58/jm0124/tempJsons/1_21.json", "total_energy": {"total_energy": -762.8229544694276}}